{
  "articles": [
    {
      "id": "article_1769046629261",
      "title": "Smartphone-Enabled Cough Detection in Severely Exacerbated COPD: An Exploratory Pilot Study.",
      "summary": "A smartphone app successfully detected cough patterns in COPD patients, potentially enabling earlier intervention and remote monitoring of disease exacerbations.",
      "url": "https://pubmed.ncbi.nlm.nih.gov/41558973/",
      "source": "PubMed",
      "category": "Diagnostic Tools",
      "cancer_types": [
        "Lung",
        "Leukemia"
      ],
      "quality_score": 15,
      "pub_date": "2026-01",
      "added_date": "2026-01-22T01:50:29.261Z"
    },
    {
      "id": "article_1769045580004",
      "title": "Endobronchial ultrasound-guided mediastinal biopsies for the diagnosis of mediastinal diseases: A network meta-analysis.",
      "summary": "A network meta-analysis shows endobronchial ultrasound-guided biopsies effectively diagnose mediastinal diseases, particularly in lung cancer staging.",
      "url": "https://pubmed.ncbi.nlm.nih.gov/41560513/",
      "source": "PubMed",
      "category": "Diagnostic Tools",
      "cancer_types": [
        "Lung"
      ],
      "quality_score": 15,
      "pub_date": "2026-01",
      "added_date": "2026-01-22T01:33:00.004Z"
    }
  ],
  "last_updated": "2026-01-22T01:50:29.261Z",
  "total_count": 2
}